chiplet/builder.py
chiplet/cli.py
chiplet/config.py
chiplet/constants.py
chiplet/render_options.py
chiplet/templates/Chipletfile.cpu.j2
chiplet/templates/Chipletfile.cu12.j2
chiplet/templates/Chipletfile.gpu.j2
chiplet/templates/Dockerfile.j2
chiplet/templates/Model.j2
chiplet-0.0.2.dist-info/METADATA
chiplet-0.0.2.dist-info/WHEEL
chiplet-0.0.2.dist-info/entry_points.txt
chiplet-0.0.2.dist-info/RECORD
